spotipyio/__init__.py
spotipyio/auth/__init__.py
spotipyio/auth/client_credentials.py
spotipyio/auth/session_cache_handler_interface.py
spotipyio/auth/spotify_grant_type.py
spotipyio/auth/spotify_session.py
spotipyio/extras/__init__.py
spotipyio/extras/redis/__init__.py
spotipyio/extras/redis/redis_session_cache_handler.py
spotipyio/logic/__init__.py
spotipyio/logic/authorization/__init__.py
spotipyio/logic/authorization/access_token_generator.py
spotipyio/logic/authorization/authorization_payload_builder.py
spotipyio/logic/collectors/__init__.py
spotipyio/logic/collectors/chunks_collectors/__init__.py
spotipyio/logic/collectors/chunks_collectors/albums_collector.py
spotipyio/logic/collectors/chunks_collectors/artists_collector.py
spotipyio/logic/collectors/chunks_collectors/audio_features_collector.py
spotipyio/logic/collectors/chunks_collectors/chapters_collector.py
spotipyio/logic/collectors/chunks_collectors/episodes_collector.py
spotipyio/logic/collectors/chunks_collectors/tracks_collector.py
spotipyio/logic/collectors/current_profile_collector.py
spotipyio/logic/collectors/pagination_collectors/__init__.py
spotipyio/logic/collectors/pagination_collectors/playlists_collector.py
spotipyio/logic/collectors/pagination_collectors/user_playlists_collector.py
spotipyio/logic/collectors/search_collectors/__init__.py
spotipyio/logic/collectors/search_collectors/search_collector.py
spotipyio/logic/collectors/singles_collectors/__init__.py
spotipyio/logic/collectors/singles_collectors/artists_top_tracks_collector.py
spotipyio/logic/collectors/top_items_collectors/__init__.py
spotipyio/logic/collectors/top_items_collectors/top_items_collector.py
spotipyio/logic/consts/__init__.py
spotipyio/logic/consts/api_consts.py
spotipyio/logic/consts/env_consts.py
spotipyio/logic/consts/image_consts.py
spotipyio/logic/consts/matching_consts.py
spotipyio/logic/consts/spotify_consts.py
spotipyio/logic/consts/typing_consts.py
spotipyio/logic/contract/__init__.py
spotipyio-1.1.1.dist-info/METADATA
spotipyio-1.1.1.dist-info/WHEEL
spotipyio-1.1.1.dist-info/RECORD
