Metadata-Version: 2.1
Name: spotipyio
Version: 1.1.1
Summary: 
Author: nirgodin
Author-email: 70273595+nirgodin@users.noreply.github.com
Requires-Python: >=3.8,<3.13
Classifier: Programming Language :: Python :: 3
Classifier: Programming Language :: Python :: 3.8
Classifier: Programming Language :: Python :: 3.9
Classifier: Programming Language :: Python :: 3.10
Classifier: Programming Language :: Python :: 3.11
Provides-Extra: redis
Provides-Extra: testing
Requires-Dist: aiohttp (>=3.9.0,<4)
Requires-Dist: asyncio-pool (>=0.6,<1.0)
Requires-Dist: certifi (>=2023.11,<2024.0)
Requires-Dist: pillow (>=10.1,<11.0)
Requires-Dist: pytest-httpserver (>=1.0.12,<1.1) ; extra == "testing"
Requires-Dist: redis (>=5.0.3,<5.1) ; extra == "redis"
Requires-Dist: tqdm (>=4.65,<5.0)
